[
    {
        "datetime": "2023-12-15T23:00:00.000000Z",
        "price": 0.0672
    },
    {
        "datetime": "2023-12-16T00:00:00.000000Z",
        "price": 0.06321
    },
    {
        "datetime": "2023-12-16T01:00:00.000000Z",
        "price": 0.06037
    },
    {
        "datetime": "2023-12-16T02:00:00.000000Z",
        "price": 0.058
    },
    {
        "datetime": "2023-12-16T03:00:00.000000Z",
        "price": 0.0541
    },
    {
        "datetime": "2023-12-16T04:00:00.000000Z",
        "price": 0.05564
    },
    {
        "datetime": "2023-12-16T05:00:00.000000Z",
        "price": 0.05934
    },
    {
        "datetime": "2023-12-16T06:00:00.000000Z",
        "price": 0.0651
    },
    {
        "datetime": "2023-12-16T07:00:00.000000Z",
        "price": 0.07989
    },
    {
        "datetime": "2023-12-16T08:00:00.000000Z",
        "price": 0.08769
    },
    {
        "datetime": "2023-12-16T09:00:00.000000Z",
        "price": 0.08442
    },
    {
        "datetime": "2023-12-16T10:00:00.000000Z",
        "price": 0.077
    },
    {
        "datetime": "2023-12-16T11:00:00.000000Z",
        "price": 0.07145
    },
    {
        "datetime": "2023-12-16T12:00:00.000000Z",
        "price": 0.07062
    },
    {
        "datetime": "2023-12-16T13:00:00.000000Z",
        "price": 0.07531
    },
    {
        "datetime": "2023-12-16T14:00:00.000000Z",
        "price": 0.08038
    },
    {
        "datetime": "2023-12-16T15:00:00.000000Z",
        "price": 0.0839
    },
    {
        "datetime": "2023-12-16T16:00:00.000000Z",
        "price": 0.10678
    },
    {
        "datetime": "2023-12-16T17:00:00.000000Z",
        "price": 0.11881
    },
    {
        "datetime": "2023-12-16T18:00:00.000000Z",
        "price": 0.103
    },
    {
        "datetime": "2023-12-16T19:00:00.000000Z",
        "price": 0.0936
    },
    {
        "datetime": "2023-12-16T20:00:00.000000Z",
        "price": 0.075
    },
    {
        "datetime": "2023-12-16T21:00:00.000000Z",
        "price": 0.06646
    },
    {
        "datetime": "2023-12-16T22:00:00.000000Z",
        "price": 0.056
    },
    {
        "datetime": "2023-12-16T23:00:00.000000Z",
        "price": 0.04548
    },
    {
        "datetime": "2023-12-17T00:00:00.000000Z",
        "price": 0.04311
    },
    {
        "datetime": "2023-12-17T01:00:00.000000Z",
        "price": 0.04371
    },
    {
        "datetime": "2023-12-17T02:00:00.000000Z",
        "price": 0.02869
    },
    {
        "datetime": "2023-12-17T03:00:00.000000Z",
        "price": 0.02637
    },
    {
        "datetime": "2023-12-17T04:00:00.000000Z",
        "price": 0.02987
    },
    {
        "datetime": "2023-12-17T05:00:00.000000Z",
        "price": 0.03903
    },
    {
        "datetime": "2023-12-17T06:00:00.000000Z",
        "price": 0.04553
    },
    {
        "datetime": "2023-12-17T07:00:00.000000Z",
        "price": 0.05767
    },
    {
        "datetime": "2023-12-17T08:00:00.000000Z",
        "price": 0.05917
    },
    {
        "datetime": "2023-12-17T09:00:00.000000Z",
        "price": 0.05443
    },
    {
        "datetime": "2023-12-17T10:00:00.000000Z",
        "price": 0.049
    },
    {
        "datetime": "2023-12-17T11:00:00.000000Z",
        "price": 0.04371
    },
    {
        "datetime": "2023-12-17T12:00:00.000000Z",
        "price": 0.04003
    },
    {
        "datetime": "2023-12-17T13:00:00.000000Z",
        "price": 0.0461
    },
    {
        "datetime": "2023-12-17T14:00:00.000000Z",
        "price": 0.05718
    },
    {
        "datetime": "2023-12-17T15:00:00.000000Z",
        "price": 0.06413
    },
    {
        "datetime": "2023-12-17T16:00:00.000000Z",
        "price": 0.089
    },
    {
        "datetime": "2023-12-17T17:00:00.000000Z",
        "price": 0.09989
    },
    {
        "datetime": "2023-12-17T18:00:00.000000Z",
        "price": 0.086
    },
    {
        "datetime": "2023-12-17T19:00:00.000000Z",
        "price": 0.06599
    },
    {
        "datetime": "2023-12-17T20:00:00.000000Z",
        "price": 0.06489
    },
    {
        "datetime": "2023-12-17T21:00:00.000000Z",
        "price": 0.06684
    },
    {
        "datetime": "2023-12-17T22:00:00.000000Z",
        "price": 0.05163
    }
]