[
    {
        "datetime": "2025-10-30T23:00:00.000000Z",
        "price": 0.238054
    },
    {
        "datetime": "2025-10-31T00:00:00.000000Z",
        "price": 0.227935
    },
    {
        "datetime": "2025-10-31T01:00:00.000000Z",
        "price": 0.224895
    },
    {
        "datetime": "2025-10-31T02:00:00.000000Z",
        "price": 0.225044
    },
    {
        "datetime": "2025-10-31T03:00:00.000000Z",
        "price": 0.228979
    },
    {
        "datetime": "2025-10-31T04:00:00.000000Z",
        "price": 0.241557
    },
    {
        "datetime": "2025-10-31T05:00:00.000000Z",
        "price": 0.273676
    },
    {
        "datetime": "2025-10-31T06:00:00.000000Z",
        "price": 0.273985
    },
    {
        "datetime": "2025-10-31T07:00:00.000000Z",
        "price": 0.26291
    },
    {
        "datetime": "2025-10-31T08:00:00.000000Z",
        "price": 0.243045
    },
    {
        "datetime": "2025-10-31T09:00:00.000000Z",
        "price": 0.23777
    },
    {
        "datetime": "2025-10-31T10:00:00.000000Z",
        "price": 0.230855
    },
    {
        "datetime": "2025-10-31T11:00:00.000000Z",
        "price": 0.232573
    },
    {
        "datetime": "2025-10-31T12:00:00.000000Z",
        "price": 0.234917
    },
    {
        "datetime": "2025-10-31T13:00:00.000000Z",
        "price": 0.25664
    },
    {
        "datetime": "2025-10-31T14:00:00.000000Z",
        "price": 0.281178
    },
    {
        "datetime": "2025-10-31T15:00:00.000000Z",
        "price": 0.285477
    },
    {
        "datetime": "2025-10-31T16:00:00.000000Z",
        "price": 0.278284
    },
    {
        "datetime": "2025-10-31T17:00:00.000000Z",
        "price": 0.264323
    },
    {
        "datetime": "2025-10-31T18:00:00.000000Z",
        "price": 0.245211
    },
    {
        "datetime": "2025-10-31T19:00:00.000000Z",
        "price": 0.237579
    },
    {
        "datetime": "2025-10-31T20:00:00.000000Z",
        "price": 0.237464
    },
    {
        "datetime": "2025-10-31T21:00:00.000000Z",
        "price": 0.233123
    },
    {
        "datetime": "2025-10-31T22:00:00.000000Z",
        "price": 0.215548
    },
    {
        "datetime": "2025-10-31T23:00:00.000000Z",
        "price": 0.205614
    },
    {
        "datetime": "2025-11-01T00:00:00.000000Z",
        "price": 0.184188
    },
    {
        "datetime": "2025-11-01T01:00:00.000000Z",
        "price": 0.171323
    },
    {
        "datetime": "2025-11-01T02:00:00.000000Z",
        "price": 0.166888
    },
    {
        "datetime": "2025-11-01T03:00:00.000000Z",
        "price": 0.162644
    },
    {
        "datetime": "2025-11-01T04:00:00.000000Z",
        "price": 0.153554
    },
    {
        "datetime": "2025-11-01T05:00:00.000000Z",
        "price": 0.154452
    },
    {
        "datetime": "2025-11-01T06:00:00.000000Z",
        "price": 0.161882
    },
    {
        "datetime": "2025-11-01T07:00:00.000000Z",
        "price": 0.178056
    },
    {
        "datetime": "2025-11-01T08:00:00.000000Z",
        "price": 0.176462
    },
    {
        "datetime": "2025-11-01T09:00:00.000000Z",
        "price": 0.166903
    },
    {
        "datetime": "2025-11-01T10:00:00.000000Z",
        "price": 0.163827
    },
    {
        "datetime": "2025-11-01T11:00:00.000000Z",
        "price": 0.170188
    },
    {
        "datetime": "2025-11-01T12:00:00.000000Z",
        "price": 0.18243
    },
    {
        "datetime": "2025-11-01T13:00:00.000000Z",
        "price": 0.203333
    },
    {
        "datetime": "2025-11-01T14:00:00.000000Z",
        "price": 0.211534
    },
    {
        "datetime": "2025-11-01T15:00:00.000000Z",
        "price": 0.231248
    },
    {
        "datetime": "2025-11-01T16:00:00.000000Z",
        "price": 0.24624
    },
    {
        "datetime": "2025-11-01T17:00:00.000000Z",
        "price": 0.251403
    },
    {
        "datetime": "2025-11-01T18:00:00.000000Z",
        "price": 0.247199
    },
    {
        "datetime": "2025-11-01T19:00:00.000000Z",
        "price": 0.240616
    },
    {
        "datetime": "2025-11-01T20:00:00.000000Z",
        "price": 0.23561
    },
    {
        "datetime": "2025-11-01T21:00:00.000000Z",
        "price": 0.238293
    },
    {
        "datetime": "2025-11-01T22:00:00.000000Z",
        "price": 0.232875
    }
]