[
    {
        "datetime": "2025-09-07T22:00:00.000000Z",
        "price": 0.238995
    },
    {
        "datetime": "2025-09-07T23:00:00.000000Z",
        "price": 0.244367
    },
    {
        "datetime": "2025-09-08T00:00:00.000000Z",
        "price": 0.249885
    },
    {
        "datetime": "2025-09-08T01:00:00.000000Z",
        "price": 0.25366
    },
    {
        "datetime": "2025-09-08T02:00:00.000000Z",
        "price": 0.2464
    },
    {
        "datetime": "2025-09-08T03:00:00.000000Z",
        "price": 0.253261
    },
    {
        "datetime": "2025-09-08T04:00:00.000000Z",
        "price": 0.275331
    },
    {
        "datetime": "2025-09-08T05:00:00.000000Z",
        "price": 0.305315
    },
    {
        "datetime": "2025-09-08T06:00:00.000000Z",
        "price": 0.295611
    },
    {
        "datetime": "2025-09-08T07:00:00.000000Z",
        "price": 0.267999
    },
    {
        "datetime": "2025-09-08T08:00:00.000000Z",
        "price": 0.248614
    },
    {
        "datetime": "2025-09-08T09:00:00.000000Z",
        "price": 0.234917
    },
    {
        "datetime": "2025-09-08T10:00:00.000000Z",
        "price": 0.22174
    },
    {
        "datetime": "2025-09-08T11:00:00.000000Z",
        "price": 0.214964
    },
    {
        "datetime": "2025-09-08T12:00:00.000000Z",
        "price": 0.224148
    },
    {
        "datetime": "2025-09-08T13:00:00.000000Z",
        "price": 0.232074
    },
    {
        "datetime": "2025-09-08T14:00:00.000000Z",
        "price": 0.256685
    },
    {
        "datetime": "2025-09-08T15:00:00.000000Z",
        "price": 0.292211
    },
    {
        "datetime": "2025-09-08T16:00:00.000000Z",
        "price": 0.370982
    },
    {
        "datetime": "2025-09-08T17:00:00.000000Z",
        "price": 0.608468
    },
    {
        "datetime": "2025-09-08T18:00:00.000000Z",
        "price": 0.494716
    },
    {
        "datetime": "2025-09-08T19:00:00.000000Z",
        "price": 0.32868
    },
    {
        "datetime": "2025-09-08T20:00:00.000000Z",
        "price": 0.292138
    },
    {
        "datetime": "2025-09-08T21:00:00.000000Z",
        "price": 0.27861
    }
]