[
    {
        "datetime": "2024-08-18T22:00:00.000000Z",
        "price": 0.271272
    },
    {
        "datetime": "2024-08-18T23:00:00.000000Z",
        "price": 0.262451
    },
    {
        "datetime": "2024-08-19T00:00:00.000000Z",
        "price": 0.260757
    },
    {
        "datetime": "2024-08-19T01:00:00.000000Z",
        "price": 0.256111
    },
    {
        "datetime": "2024-08-19T02:00:00.000000Z",
        "price": 0.255675
    },
    {
        "datetime": "2024-08-19T03:00:00.000000Z",
        "price": 0.258422
    },
    {
        "datetime": "2024-08-19T04:00:00.000000Z",
        "price": 0.302079
    },
    {
        "datetime": "2024-08-19T05:00:00.000000Z",
        "price": 0.334652
    },
    {
        "datetime": "2024-08-19T06:00:00.000000Z",
        "price": 0.309097
    },
    {
        "datetime": "2024-08-19T07:00:00.000000Z",
        "price": 0.289652
    },
    {
        "datetime": "2024-08-19T08:00:00.000000Z",
        "price": 0.269687
    },
    {
        "datetime": "2024-08-19T09:00:00.000000Z",
        "price": 0.260769
    },
    {
        "datetime": "2024-08-19T10:00:00.000000Z",
        "price": 0.254126
    },
    {
        "datetime": "2024-08-19T11:00:00.000000Z",
        "price": 0.247798
    },
    {
        "datetime": "2024-08-19T12:00:00.000000Z",
        "price": 0.24896
    },
    {
        "datetime": "2024-08-19T13:00:00.000000Z",
        "price": 0.249262
    },
    {
        "datetime": "2024-08-19T14:00:00.000000Z",
        "price": 0.250593
    },
    {
        "datetime": "2024-08-19T15:00:00.000000Z",
        "price": 0.272821
    },
    {
        "datetime": "2024-08-19T16:00:00.000000Z",
        "price": 0.282948
    },
    {
        "datetime": "2024-08-19T17:00:00.000000Z",
        "price": 0.34703
    },
    {
        "datetime": "2024-08-19T18:00:00.000000Z",
        "price": 0.396567
    },
    {
        "datetime": "2024-08-19T19:00:00.000000Z",
        "price": 0.321596
    },
    {
        "datetime": "2024-08-19T20:00:00.000000Z",
        "price": 0.275701
    },
    {
        "datetime": "2024-08-19T21:00:00.000000Z",
        "price": 0.257889
    },
    {
        "datetime": "2024-08-19T22:00:00.000000Z",
        "price": 0.265791
    },
    {
        "datetime": "2024-08-19T23:00:00.000000Z",
        "price": 0.260346
    },
    {
        "datetime": "2024-08-20T00:00:00.000000Z",
        "price": 0.258422
    },
    {
        "datetime": "2024-08-20T01:00:00.000000Z",
        "price": 0.257768
    },
    {
        "datetime": "2024-08-20T02:00:00.000000Z",
        "price": 0.254029
    },
    {
        "datetime": "2024-08-20T03:00:00.000000Z",
        "price": 0.258446
    },
    {
        "datetime": "2024-08-20T04:00:00.000000Z",
        "price": 0.29834
    },
    {
        "datetime": "2024-08-20T05:00:00.000000Z",
        "price": 0.299489
    },
    {
        "datetime": "2024-08-20T06:00:00.000000Z",
        "price": 0.285671
    },
    {
        "datetime": "2024-08-20T07:00:00.000000Z",
        "price": 0.27714
    },
    {
        "datetime": "2024-08-20T08:00:00.000000Z",
        "price": 0.226732
    },
    {
        "datetime": "2024-08-20T09:00:00.000000Z",
        "price": 0.210191
    },
    {
        "datetime": "2024-08-20T10:00:00.000000Z",
        "price": 0.193179
    },
    {
        "datetime": "2024-08-20T11:00:00.000000Z",
        "price": 0.172875
    },
    {
        "datetime": "2024-08-20T12:00:00.000000Z",
        "price": 0.163413
    },
    {
        "datetime": "2024-08-20T13:00:00.000000Z",
        "price": 0.186354
    },
    {
        "datetime": "2024-08-20T14:00:00.000000Z",
        "price": 0.213833
    },
    {
        "datetime": "2024-08-20T15:00:00.000000Z",
        "price": 0.274745
    },
    {
        "datetime": "2024-08-20T16:00:00.000000Z",
        "price": 0.294806
    },
    {
        "datetime": "2024-08-20T17:00:00.000000Z",
        "price": 0.303059
    },
    {
        "datetime": "2024-08-20T18:00:00.000000Z",
        "price": 0.328977
    },
    {
        "datetime": "2024-08-20T19:00:00.000000Z",
        "price": 0.29863
    },
    {
        "datetime": "2024-08-20T20:00:00.000000Z",
        "price": 0.278568
    },
    {
        "datetime": "2024-08-20T21:00:00.000000Z",
        "price": 0.268005
    }
]