[
    {
        "datetime": "2025-01-16T23:00:00.000000Z",
        "price": 0.26576
    },
    {
        "datetime": "2025-01-17T00:00:00.000000Z",
        "price": 0.27786
    },
    {
        "datetime": "2025-01-17T01:00:00.000000Z",
        "price": 0.273444
    },
    {
        "datetime": "2025-01-17T02:00:00.000000Z",
        "price": 0.272899
    },
    {
        "datetime": "2025-01-17T03:00:00.000000Z",
        "price": 0.273093
    },
    {
        "datetime": "2025-01-17T04:00:00.000000Z",
        "price": 0.28028
    },
    {
        "datetime": "2025-01-17T05:00:00.000000Z",
        "price": 0.315128
    },
    {
        "datetime": "2025-01-17T06:00:00.000000Z",
        "price": 0.356522
    },
    {
        "datetime": "2025-01-17T07:00:00.000000Z",
        "price": 0.396597
    },
    {
        "datetime": "2025-01-17T08:00:00.000000Z",
        "price": 0.356921
    },
    {
        "datetime": "2025-01-17T09:00:00.000000Z",
        "price": 0.334524
    },
    {
        "datetime": "2025-01-17T10:00:00.000000Z",
        "price": 0.314281
    },
    {
        "datetime": "2025-01-17T11:00:00.000000Z",
        "price": 0.297752
    },
    {
        "datetime": "2025-01-17T12:00:00.000000Z",
        "price": 0.294836
    },
    {
        "datetime": "2025-01-17T13:00:00.000000Z",
        "price": 0.303512
    },
    {
        "datetime": "2025-01-17T14:00:00.000000Z",
        "price": 0.323465
    },
    {
        "datetime": "2025-01-17T15:00:00.000000Z",
        "price": 0.344434
    },
    {
        "datetime": "2025-01-17T16:00:00.000000Z",
        "price": 0.359838
    },
    {
        "datetime": "2025-01-17T17:00:00.000000Z",
        "price": 0.362463
    },
    {
        "datetime": "2025-01-17T18:00:00.000000Z",
        "price": 0.355566
    },
    {
        "datetime": "2025-01-17T19:00:00.000000Z",
        "price": 0.335831
    },
    {
        "datetime": "2025-01-17T20:00:00.000000Z",
        "price": 0.32021
    },
    {
        "datetime": "2025-01-17T21:00:00.000000Z",
        "price": 0.314124
    },
    {
        "datetime": "2025-01-17T22:00:00.000000Z",
        "price": 0.298297
    }
]