[
    {
        "datetime": "2025-08-03T22:00:00.000000Z",
        "price": 0.242831
    },
    {
        "datetime": "2025-08-03T23:00:00.000000Z",
        "price": 0.229545
    },
    {
        "datetime": "2025-08-04T00:00:00.000000Z",
        "price": 0.229424
    },
    {
        "datetime": "2025-08-04T01:00:00.000000Z",
        "price": 0.234566
    },
    {
        "datetime": "2025-08-04T02:00:00.000000Z",
        "price": 0.236345
    },
    {
        "datetime": "2025-08-04T03:00:00.000000Z",
        "price": 0.248155
    },
    {
        "datetime": "2025-08-04T04:00:00.000000Z",
        "price": 0.263437
    },
    {
        "datetime": "2025-08-04T05:00:00.000000Z",
        "price": 0.27394
    },
    {
        "datetime": "2025-08-04T06:00:00.000000Z",
        "price": 0.271883
    },
    {
        "datetime": "2025-08-04T07:00:00.000000Z",
        "price": 0.266873
    },
    {
        "datetime": "2025-08-04T08:00:00.000000Z",
        "price": 0.239576
    },
    {
        "datetime": "2025-08-04T09:00:00.000000Z",
        "price": 0.204703
    },
    {
        "datetime": "2025-08-04T10:00:00.000000Z",
        "price": 0.160986
    },
    {
        "datetime": "2025-08-04T11:00:00.000000Z",
        "price": 0.149661
    },
    {
        "datetime": "2025-08-04T12:00:00.000000Z",
        "price": 0.145547
    },
    {
        "datetime": "2025-08-04T13:00:00.000000Z",
        "price": 0.144784
    },
    {
        "datetime": "2025-08-04T14:00:00.000000Z",
        "price": 0.1583
    },
    {
        "datetime": "2025-08-04T15:00:00.000000Z",
        "price": 0.191079
    },
    {
        "datetime": "2025-08-04T16:00:00.000000Z",
        "price": 0.223507
    },
    {
        "datetime": "2025-08-04T17:00:00.000000Z",
        "price": 0.245964
    },
    {
        "datetime": "2025-08-04T18:00:00.000000Z",
        "price": 0.242238
    },
    {
        "datetime": "2025-08-04T19:00:00.000000Z",
        "price": 0.234046
    },
    {
        "datetime": "2025-08-04T20:00:00.000000Z",
        "price": 0.225891
    },
    {
        "datetime": "2025-08-04T21:00:00.000000Z",
        "price": 0.203554
    },
    {
        "datetime": "2025-08-04T22:00:00.000000Z",
        "price": 0.16896
    },
    {
        "datetime": "2025-08-04T23:00:00.000000Z",
        "price": 0.160672
    },
    {
        "datetime": "2025-08-05T00:00:00.000000Z",
        "price": 0.16124
    },
    {
        "datetime": "2025-08-05T01:00:00.000000Z",
        "price": 0.169517
    },
    {
        "datetime": "2025-08-05T02:00:00.000000Z",
        "price": 0.201098
    },
    {
        "datetime": "2025-08-05T03:00:00.000000Z",
        "price": 0.226846
    },
    {
        "datetime": "2025-08-05T04:00:00.000000Z",
        "price": 0.24496
    },
    {
        "datetime": "2025-08-05T05:00:00.000000Z",
        "price": 0.244851
    },
    {
        "datetime": "2025-08-05T06:00:00.000000Z",
        "price": 0.221038
    },
    {
        "datetime": "2025-08-05T07:00:00.000000Z",
        "price": 0.149007
    },
    {
        "datetime": "2025-08-05T08:00:00.000000Z",
        "price": 0.142945
    },
    {
        "datetime": "2025-08-05T09:00:00.000000Z",
        "price": 0.1375
    },
    {
        "datetime": "2025-08-05T10:00:00.000000Z",
        "price": 0.129974
    },
    {
        "datetime": "2025-08-05T11:00:00.000000Z",
        "price": 0.109561
    },
    {
        "datetime": "2025-08-05T12:00:00.000000Z",
        "price": 0.118176
    },
    {
        "datetime": "2025-08-05T13:00:00.000000Z",
        "price": 0.129441
    },
    {
        "datetime": "2025-08-05T14:00:00.000000Z",
        "price": 0.131208
    },
    {
        "datetime": "2025-08-05T15:00:00.000000Z",
        "price": 0.142667
    },
    {
        "datetime": "2025-08-05T16:00:00.000000Z",
        "price": 0.145813
    },
    {
        "datetime": "2025-08-05T17:00:00.000000Z",
        "price": 0.230718
    },
    {
        "datetime": "2025-08-05T18:00:00.000000Z",
        "price": 0.25274
    },
    {
        "datetime": "2025-08-05T19:00:00.000000Z",
        "price": 0.270927
    },
    {
        "datetime": "2025-08-05T20:00:00.000000Z",
        "price": 0.262433
    },
    {
        "datetime": "2025-08-05T21:00:00.000000Z",
        "price": 0.2464
    }
]