[
    {
        "datetime": "2024-08-15T22:00:00.000000Z",
        "price": 0.25507
    },
    {
        "datetime": "2024-08-15T23:00:00.000000Z",
        "price": 0.241893
    },
    {
        "datetime": "2024-08-16T00:00:00.000000Z",
        "price": 0.254405
    },
    {
        "datetime": "2024-08-16T01:00:00.000000Z",
        "price": 0.252771
    },
    {
        "datetime": "2024-08-16T02:00:00.000000Z",
        "price": 0.255336
    },
    {
        "datetime": "2024-08-16T03:00:00.000000Z",
        "price": 0.261156
    },
    {
        "datetime": "2024-08-16T04:00:00.000000Z",
        "price": 0.299138
    },
    {
        "datetime": "2024-08-16T05:00:00.000000Z",
        "price": 0.306531
    },
    {
        "datetime": "2024-08-16T06:00:00.000000Z",
        "price": 0.29863
    },
    {
        "datetime": "2024-08-16T07:00:00.000000Z",
        "price": 0.286542
    },
    {
        "datetime": "2024-08-16T08:00:00.000000Z",
        "price": 0.27443
    },
    {
        "datetime": "2024-08-16T09:00:00.000000Z",
        "price": 0.261846
    },
    {
        "datetime": "2024-08-16T10:00:00.000000Z",
        "price": 0.243442
    },
    {
        "datetime": "2024-08-16T11:00:00.000000Z",
        "price": 0.218165
    },
    {
        "datetime": "2024-08-16T12:00:00.000000Z",
        "price": 0.211159
    },
    {
        "datetime": "2024-08-16T13:00:00.000000Z",
        "price": 0.219073
    },
    {
        "datetime": "2024-08-16T14:00:00.000000Z",
        "price": 0.248403
    },
    {
        "datetime": "2024-08-16T15:00:00.000000Z",
        "price": 0.270764
    },
    {
        "datetime": "2024-08-16T16:00:00.000000Z",
        "price": 0.3056
    },
    {
        "datetime": "2024-08-16T17:00:00.000000Z",
        "price": 0.405993
    },
    {
        "datetime": "2024-08-16T18:00:00.000000Z",
        "price": 0.418723
    },
    {
        "datetime": "2024-08-16T19:00:00.000000Z",
        "price": 0.347986
    },
    {
        "datetime": "2024-08-16T20:00:00.000000Z",
        "price": 0.312848
    },
    {
        "datetime": "2024-08-16T21:00:00.000000Z",
        "price": 0.294008
    }
]