[
    {
        "datetime": "2023-05-23T22:00:00.000000Z",
        "price": 0.274755
    },
    {
        "datetime": "2023-05-23T23:00:00.000000Z",
        "price": 0.266394
    },
    {
        "datetime": "2023-05-24T00:00:00.000000Z",
        "price": 0.265232
    },
    {
        "datetime": "2023-05-24T01:00:00.000000Z",
        "price": 0.266309
    },
    {
        "datetime": "2023-05-24T02:00:00.000000Z",
        "price": 0.266817
    },
    {
        "datetime": "2023-05-24T03:00:00.000000Z",
        "price": 0.277816
    },
    {
        "datetime": "2023-05-24T04:00:00.000000Z",
        "price": 0.302077
    },
    {
        "datetime": "2023-05-24T05:00:00.000000Z",
        "price": 0.321304
    },
    {
        "datetime": "2023-05-24T06:00:00.000000Z",
        "price": 0.307014
    },
    {
        "datetime": "2023-05-24T07:00:00.000000Z",
        "price": 0.292542
    },
    {
        "datetime": "2023-05-24T08:00:00.000000Z",
        "price": 0.278288
    },
    {
        "datetime": "2023-05-24T09:00:00.000000Z",
        "price": 0.272335
    },
    {
        "datetime": "2023-05-24T10:00:00.000000Z",
        "price": 0.271827
    },
    {
        "datetime": "2023-05-24T11:00:00.000000Z",
        "price": 0.260332
    },
    {
        "datetime": "2023-05-24T12:00:00.000000Z",
        "price": 0.265329
    },
    {
        "datetime": "2023-05-24T13:00:00.000000Z",
        "price": 0.256121
    },
    {
        "datetime": "2023-05-24T14:00:00.000000Z",
        "price": 0.271125
    },
    {
        "datetime": "2023-05-24T15:00:00.000000Z",
        "price": 0.269879
    },
    {
        "datetime": "2023-05-24T16:00:00.000000Z",
        "price": 0.307389
    },
    {
        "datetime": "2023-05-24T17:00:00.000000Z",
        "price": 0.338885
    },
    {
        "datetime": "2023-05-24T18:00:00.000000Z",
        "price": 0.346145
    },
    {
        "datetime": "2023-05-24T19:00:00.000000Z",
        "price": 0.353889
    },
    {
        "datetime": "2023-05-24T20:00:00.000000Z",
        "price": 0.313039
    },
    {
        "datetime": "2023-05-24T21:00:00.000000Z",
        "price": 0.298907
    }
]